kevin_mysql_sync/check_info.json
kevin_mysql_sync/log.txt
kevin_mysql_sync/main.py
kevin_mysql_sync-0.1.0.dist-info/METADATA
kevin_mysql_sync-0.1.0.dist-info/WHEEL
kevin_mysql_sync-0.1.0.dist-info/RECORD
